pyEDAA/ToolSetup/DataModel.py
pyEDAA/ToolSetup/Interface.py
pyEDAA/ToolSetup/__init__.py
pyEDAA/ToolSetup/Aldec/__init__.py
pyEDAA/ToolSetup/CLI/Configure.py
pyEDAA/ToolSetup/CLI/__init__.py
pyEDAA/ToolSetup/IntelFPGA/__init__.py
pyEDAA/ToolSetup/Lattice/__init__.py
pyEDAA/ToolSetup/OpenSource/GHDL.py
pyEDAA/ToolSetup/OpenSource/GTKWave.py
pyEDAA/ToolSetup/OpenSource/__init__.py
pyEDAA/ToolSetup/SiemensEDA/__init__.py
pyEDAA/ToolSetup/SystemTools/__init__.py
pyEDAA/ToolSetup/Xilinx/__init__.py
pyedaa_toolsetup-0.4.0.dist-info/licenses/LICENSE.md
pyedaa_toolsetup-0.4.0.dist-info/METADATA
pyedaa_toolsetup-0.4.0.dist-info/WHEEL
pyedaa_toolsetup-0.4.0.dist-info/entry_points.txt
pyedaa_toolsetup-0.4.0.dist-info/top_level.txt
pyedaa_toolsetup-0.4.0.dist-info/RECORD
