Metadata-Version: 2.4
Name: pyEDAA.ToolSetup
Version: 0.4.0
Summary: EDA tool detection, configuration and selection layer.
Home-page: https://GitHub.com/edaa-org/pyEDAA.ToolSetup
Author: Patrick Lehmann
Author-email: Paebbels@gmail.com
License: Apache-2.0
Project-URL: Documentation, https://edaa-org.GitHub.io/pyEDAA.ToolSetup
Project-URL: Source Code, https://GitHub.com/edaa-org/pyEDAA.ToolSetup
Project-URL: Issue Tracker, https://GitHub.com/edaa-org/pyEDAA.ToolSetup/issues
Keywords: configuration,eda,installation,selection
Classifier: Operating System :: OS Independent
Classifier: Intended Audience :: Developers
Classifier: Topic :: Utilities
Classifier: Topic :: Scientific/Engineering :: Electronic Design Automation (EDA)
Classifier: License :: OSI Approved :: Apache Software License
Classifier: Programming Language :: Python :: 3 :: Only
Classifier: Programming Language :: Python :: 3.9
Classifier: Programming Language :: Python :: 3.10
Classifier: Programming Language :: Python :: 3.11
Classifier: Programming Language :: Python :: 3.12
Classifier: Programming Language :: Python :: 3.13
Classifier: Development Status :: 3 - Alpha
Requires-Python: >=3.9
License-File: LICENSE.md
Requires-Dist: pyEDAA.CLITool~=0.3
Requires-Dist: pyTooling[yaml]~=8.4
Provides-Extra: doc
Requires-Dist: docutils~=0.21; extra == "doc"
Requires-Dist: sphinx~=8.2; extra == "doc"
Requires-Dist: sphinx_design~=0.6.1; extra == "doc"
Requires-Dist: sphinx_reports~=0.9; extra == "doc"
Requires-Dist: sphinxcontrib-mermaid~=1.0; extra == "doc"
Requires-Dist: sphinx-copybutton>=0.5.2; extra == "doc"
Requires-Dist: pyTooling[yaml]~=8.4; extra == "doc"
Requires-Dist: docutils_stubs~=0.0.22; extra == "doc"
Requires-Dist: pyEDAA.CLITool~=0.3; extra == "doc"
Requires-Dist: sphinx_autodoc_typehints~=3.2; extra == "doc"
Requires-Dist: sphinx_rtd_theme~=3.0; extra == "doc"
Requires-Dist: autoapi>=2.0.1; extra == "doc"
Provides-Extra: test
Requires-Dist: pytest-cov~=6.1; extra == "test"
Requires-Dist: pytest~=8.3; extra == "test"
Requires-Dist: typing_extensions~=4.13; extra == "test"
Requires-Dist: pyTooling[yaml]~=8.4; extra == "test"
Requires-Dist: Coverage~=7.8; extra == "test"
Requires-Dist: lxml~=5.4; extra == "test"
Requires-Dist: pyEDAA.CLITool~=0.3; extra == "test"
Requires-Dist: mypy~=1.15; extra == "test"
Provides-Extra: all
Requires-Dist: sphinx_design~=0.6.1; extra == "all"
Requires-Dist: docutils~=0.21; extra == "all"
Requires-Dist: sphinx~=8.2; extra == "all"
Requires-Dist: sphinx_reports~=0.9; extra == "all"
Requires-Dist: pytest-cov~=6.1; extra == "all"
Requires-Dist: sphinxcontrib-mermaid~=1.0; extra == "all"
Requires-Dist: sphinx-copybutton>=0.5.2; extra == "all"
Requires-Dist: pytest~=8.3; extra == "all"
Requires-Dist: typing_extensions~=4.13; extra == "all"
Requires-Dist: pyTooling[yaml]~=8.4; extra == "all"
Requires-Dist: docutils_stubs~=0.0.22; extra == "all"
Requires-Dist: Coverage~=7.8; extra == "all"
Requires-Dist: lxml~=5.4; extra == "all"
Requires-Dist: pyEDAA.CLITool~=0.3; extra == "all"
Requires-Dist: mypy~=1.15; extra == "all"
Requires-Dist: sphinx_autodoc_typehints~=3.2; extra == "all"
Requires-Dist: sphinx_rtd_theme~=3.0; extra == "all"
Requires-Dist: autoapi>=2.0.1; extra == "all"
Dynamic: author
Dynamic: author-email
Dynamic: classifier
Dynamic: description
Dynamic: description-content-type
Dynamic: home-page
Dynamic: keywords
Dynamic: license
Dynamic: license-file
Dynamic: project-url
Dynamic: provides-extra
Dynamic: requires-dist
Dynamic: requires-python
Dynamic: summary
